test/Mergefile.py
test/Person.py
test/__init__.py
test/operations.py
test/setup.py
python_track-1.1.dist-info/METADATA
python_track-1.1.dist-info/WHEEL
python_track-1.1.dist-info/top_level.txt
python_track-1.1.dist-info/RECORD
