Metadata-Version: 2.1
Name: python-track
Version: 1.1
Summary: Creating python package
Home-page: https://github.com/shahKrinal/Python_package/tree/main
Author: krinal
Author-email: shahkrinal877@gmail.com
License: UNKNOWN
Platform: UNKNOWN
